odoo/addons/fieldservice_geoengine/README.rst
odoo/addons/fieldservice_geoengine/__init__.py
odoo/addons/fieldservice_geoengine/__manifest__.py
odoo/addons/fieldservice_geoengine/i18n/de.po
odoo/addons/fieldservice_geoengine/i18n/es.po
odoo/addons/fieldservice_geoengine/i18n/es_AR.po
odoo/addons/fieldservice_geoengine/i18n/es_CL.po
odoo/addons/fieldservice_geoengine/i18n/fieldservice_geoengine.pot
odoo/addons/fieldservice_geoengine/i18n/fr_FR.po
odoo/addons/fieldservice_geoengine/i18n/it.po
odoo/addons/fieldservice_geoengine/i18n/pt_BR.po
odoo/addons/fieldservice_geoengine/models/__init__.py
odoo/addons/fieldservice_geoengine/models/fsm_location.py
odoo/addons/fieldservice_geoengine/models/fsm_order.py
odoo/addons/fieldservice_geoengine/readme/CONFIGURE.rst
odoo/addons/fieldservice_geoengine/readme/CONTRIBUTORS.rst
odoo/addons/fieldservice_geoengine/readme/CREDITS.rst
odoo/addons/fieldservice_geoengine/readme/DESCRIPTION.rst
odoo/addons/fieldservice_geoengine/readme/INSTALL.rst
odoo/addons/fieldservice_geoengine/readme/ROADMAP.rst
odoo/addons/fieldservice_geoengine/readme/USAGE.rst
odoo/addons/fieldservice_geoengine/security/res_groups.xml
odoo/addons/fieldservice_geoengine/static/description/icon.png
odoo/addons/fieldservice_geoengine/static/description/index.html
odoo/addons/fieldservice_geoengine/tests/__init__.py
odoo/addons/fieldservice_geoengine/tests/test_fsm_location.py
odoo/addons/fieldservice_geoengine/views/fsm_location.xml
odoo/addons/fieldservice_geoengine/views/fsm_order.xml
odoo/addons/fieldservice_geoengine/views/fsm_team.xml
odoo14_addon_fieldservice_geoengine-14.0.1.3.0.dist-info/METADATA
odoo14_addon_fieldservice_geoengine-14.0.1.3.0.dist-info/WHEEL
odoo14_addon_fieldservice_geoengine-14.0.1.3.0.dist-info/top_level.txt
odoo14_addon_fieldservice_geoengine-14.0.1.3.0.dist-info/RECORD
