Metadata-Version: 2.1
Name: odoo14-addon-fieldservice_geoengine
Version: 14.0.1.3.0
Summary: Display Field Service locations on a map with Open Street Map
Home-page: https://github.com/OCA/field-service
Author: Open Source Integrators, Odoo Community Association (OCA), Pytech SRL
Author-email: support@odoo-community.org
License: AGPL-3
Classifier: Programming Language :: Python
Classifier: Framework :: Odoo
Classifier: Framework :: Odoo :: 14.0
Classifier: License :: OSI Approved :: GNU Affero General Public License v3
Classifier: Development Status :: 4 - Beta
Requires-Python: >=3.6
Requires-Dist: odoo14-addon-base-geoengine
Requires-Dist: odoo14-addon-fieldservice
Requires-Dist: odoo<14.1dev,>=14.0a
